Metadata-Version: 1.1
Name: sphinxcontrib-excel-table
Version: 1.0.3
Summary: Embed excel file as an excel-alike table into sphinx documentation.
Home-page: https://github.com/hackerain/sphinxcontrib-excel-table
Author: Guangyu Suo
Author-email: yugsuo@gmail.com
License: Apache License
Download-URL: https://github.com/hackerain/sphinxcontrib-excel-table/archive/1.0.3.tar.gz
Keywords: python,sphinx,excel
Platform: UNKNOWN
Classifier: Topic :: Office/Business
Classifier: Topic :: Utilities
Classifier: Topic :: Software Development :: Libraries
Classifier: Programming Language :: Python
Classifier: Intended Audience :: Developers
Classifier: Programming Language :: Python :: 2.6
Classifier: Programming Language :: Python :: 2.7
Classifier: Programming Language :: Python :: 3.3
Classifier: Programming Language :: Python :: 3.4
Classifier: Programming Language :: Python :: 3.5
Classifier: Programming Language :: Python :: 3.6
Classifier: License :: OSI Approved :: Apache Software License
